docugenr8_pdf/__init__.py
docugenr8_pdf/core.py
docugenr8_pdf/pdf.py
docugenr8_pdf/pdf_content.py
docugenr8_pdf/pdf_font.py
docugenr8_pdf/pdf_info.py
docugenr8_pdf/pdf_page.py
docugenr8_pdf/pdf_settings.py
docugenr8_pdf-0.0.6.dist-info/LICENSE
docugenr8_pdf-0.0.6.dist-info/METADATA
docugenr8_pdf-0.0.6.dist-info/WHEEL
docugenr8_pdf-0.0.6.dist-info/top_level.txt
docugenr8_pdf-0.0.6.dist-info/RECORD
