Metadata-Version: 2.1
Name: docugenr8-pdf
Version: 0.0.6
Summary: Docugenr8 add-on library that generates pdf documents.
Author-email: Vladimir Jovanovic <vladimirjo@protonmail.com>
License: MIT
Keywords: docugenr8,core,PDF,image-integration,coordinate-system,text-formatting,python
Classifier: Programming Language :: Python :: 3
Requires-Python: >=3.10
License-File: LICENSE
Requires-Dist: fonttools
Requires-Dist: docugenr8-shared <1.0.0,>=0.0.0
Provides-Extra: build
Requires-Dist: build ; extra == 'build'
Requires-Dist: setuptools ; extra == 'build'
Requires-Dist: twine ; extra == 'build'
Provides-Extra: check
Requires-Dist: ruff ; extra == 'check'
Requires-Dist: mypy ; extra == 'check'
Provides-Extra: dev
Requires-Dist: docugenr8-pdf[build,check,test] ; extra == 'dev'
Provides-Extra: test
Requires-Dist: pytest ; extra == 'test'
Requires-Dist: pytest-cov ; extra == 'test'
